bitscrunch_unleashnftV2_sdk/Nft.py
bitscrunch_unleashnftV2_sdk/Supported_Blockchain.py
bitscrunch_unleashnftV2_sdk/Wallet.py
bitscrunch_unleashnftV2_sdk/__init__.py
bitscrunch_unleashnftV2_sdk/brand.py
bitscrunch_unleashnftV2_sdk/collection.py
bitscrunch_unleashnftV2_sdk/defi.py
bitscrunch_unleashnftV2_sdk/exceptions.py
bitscrunch_unleashnftV2_sdk/gaming.py
bitscrunch_unleashnftV2_sdk/market_insights.py
bitscrunch_unleashnftV2_sdk/marketplace.py
bitscrunch_unleashnftV2_sdk/nft_wallets.py
bitscrunch_unleashnftV2_sdk/price_estimate.py
bitscrunch_unleashnftV2_sdk/token.py
bitscrunch_unleashnftV2_sdk/transactions.py
tests/__init__.py
bitscrunch_unleashnftV2_sdk-2.0.0.dist-info/METADATA
bitscrunch_unleashnftV2_sdk-2.0.0.dist-info/WHEEL
bitscrunch_unleashnftV2_sdk-2.0.0.dist-info/top_level.txt
bitscrunch_unleashnftV2_sdk-2.0.0.dist-info/RECORD
