Metadata-Version: 2.1
Name: bitscrunch_unleashnftV2_sdk
Version: 2.0.0
Summary: A Python SDK for interacting with the bitsCrunch API V2
Author: Anupama
Author-email: anupamarawat71@gmail.com
Requires-Dist: requests
